{"config":{"output_file":null,"full_docs":false,"pub_only":true,"reachable_only":true,"distro_crate":false,"signatures":false,"borrow_data":false},"version":"0.19.1","compilation":{"directory":"C:\\Users\\Maxime\\.cargo\\registry\\src\\github.com-1ecc6299db9ec823\\rustc_version-0.1.7","program":"C:\\Users\\Maxime\\.rustup\\toolchains\\stable-x86_64-pc-windows-msvc\\bin\\rls.exe","arguments":["--crate-name","rustc_version","C:\\Users\\Maxime\\.cargo\\registry\\src\\github.com-1ecc6299db9ec823\\rustc_version-0.1.7\\src\\lib.rs","--json=diagnostic-rendered-ansi","--crate-type","lib","--emit=dep-info,metadata,link","-C","embed-bitcode=no","-C","debuginfo=2","-C","metadata=d149a016fbf0cc18","-C","extra-filename=-d149a016fbf0cc18","--out-dir","d:\\Maxime\\CodingStuff\\Langs\\Glace\\examples\\helloGPU\\target\\rls\\debug\\deps","-L","dependency=d:\\Maxime\\CodingStuff\\Langs\\Glace\\examples\\helloGPU\\target\\rls\\debug\\deps","--extern","semver=d:\\Maxime\\CodingStuff\\Langs\\Glace\\examples\\helloGPU\\target\\rls\\debug\\deps\\libsemver-62c88a6a8353d929.rmeta","--cap-lints","allow","--error-format=json","--sysroot","C:\\Users\\Maxime\\.rustup/toolchains/stable-x86_64-pc-windows-msvc"],"output":"d:\\Maxime\\CodingStuff\\Langs\\Glace\\examples\\helloGPU\\target\\rls\\debug\\deps\\librustc_version-d149a016fbf0cc18.rmeta"},"prelude":{"crate_id":{"name":"rustc_version","disambiguator":[5723145559678020553,3410316931477462060]},"crate_root":"C:\\Users\\Maxime\\.cargo\\registry\\src\\github.com-1ecc6299db9ec823\\rustc_version-0.1.7\\src","external_crates":[{"file_name":"C:\\Users\\Maxime\\.cargo\\registry\\src\\github.com-1ecc6299db9ec823\\rustc_version-0.1.7\\src\\lib.rs","num":1,"id":{"name":"std","disambiguator":[15394396593765937133,15104794829170053384]}},{"file_name":"C:\\Users\\Maxime\\.cargo\\registry\\src\\github.com-1ecc6299db9ec823\\rustc_version-0.1.7\\src\\lib.rs","num":2,"id":{"name":"core","disambiguator":[14223085168939843507,9453778982390123811]}},{"file_name":"C:\\Users\\Maxime\\.cargo\\registry\\src\\github.com-1ecc6299db9ec823\\rustc_version-0.1.7\\src\\lib.rs","num":3,"id":{"name":"compiler_builtins","disambiguator":[10495964697894269666,7444397110794681726]}},{"file_name":"C:\\Users\\Maxime\\.cargo\\registry\\src\\github.com-1ecc6299db9ec823\\rustc_version-0.1.7\\src\\lib.rs","num":4,"id":{"name":"rustc_std_workspace_core","disambiguator":[5630579929119936438,10747952327389013202]}},{"file_name":"C:\\Users\\Maxime\\.cargo\\registry\\src\\github.com-1ecc6299db9ec823\\rustc_version-0.1.7\\src\\lib.rs","num":5,"id":{"name":"alloc","disambiguator":[755004289757070725,4528322009891643596]}},{"file_name":"C:\\Users\\Maxime\\.cargo\\registry\\src\\github.com-1ecc6299db9ec823\\rustc_version-0.1.7\\src\\lib.rs","num":6,"id":{"name":"libc","disambiguator":[12293211462733931105,3605749939090106910]}},{"file_name":"C:\\Users\\Maxime\\.cargo\\registry\\src\\github.com-1ecc6299db9ec823\\rustc_version-0.1.7\\src\\lib.rs","num":7,"id":{"name":"unwind","disambiguator":[14880717690889174640,9014378682587101436]}},{"file_name":"C:\\Users\\Maxime\\.cargo\\registry\\src\\github.com-1ecc6299db9ec823\\rustc_version-0.1.7\\src\\lib.rs","num":8,"id":{"name":"cfg_if","disambiguator":[1733233879246965746,6308927592973156139]}},{"file_name":"C:\\Users\\Maxime\\.cargo\\registry\\src\\github.com-1ecc6299db9ec823\\rustc_version-0.1.7\\src\\lib.rs","num":9,"id":{"name":"hashbrown","disambiguator":[2578852399168599952,875302055328020592]}},{"file_name":"C:\\Users\\Maxime\\.cargo\\registry\\src\\github.com-1ecc6299db9ec823\\rustc_version-0.1.7\\src\\lib.rs","num":10,"id":{"name":"rustc_std_workspace_alloc","disambiguator":[15050766551219055192,6843698544963456792]}},{"file_name":"C:\\Users\\Maxime\\.cargo\\registry\\src\\github.com-1ecc6299db9ec823\\rustc_version-0.1.7\\src\\lib.rs","num":11,"id":{"name":"rustc_demangle","disambiguator":[14716868785672998615,14481457355720881040]}},{"file_name":"C:\\Users\\Maxime\\.cargo\\registry\\src\\github.com-1ecc6299db9ec823\\rustc_version-0.1.7\\src\\lib.rs","num":12,"id":{"name":"panic_unwind","disambiguator":[7183069464598737283,14932178614966804545]}},{"file_name":"C:\\Users\\Maxime\\.cargo\\registry\\src\\github.com-1ecc6299db9ec823\\rustc_version-0.1.7\\src\\lib.rs","num":13,"id":{"name":"semver","disambiguator":[5899417264422724453,12391297013038331755]}}],"span":{"file_name":"C:\\Users\\Maxime\\.cargo\\registry\\src\\github.com-1ecc6299db9ec823\\rustc_version-0.1.7\\src\\lib.rs","byte_start":350,"byte_end":8879,"line_start":9,"line_end":292,"column_start":1,"column_end":2}},"imports":[],"defs":[{"kind":"Mod","id":{"krate":0,"index":0},"span":{"file_name":"C:\\Users\\Maxime\\.cargo\\registry\\src\\github.com-1ecc6299db9ec823\\rustc_version-0.1.7\\src\\lib.rs","byte_start":350,"byte_end":8879,"line_start":9,"line_end":292,"column_start":1,"column_end":2},"name":"","qualname":"::","value":"C:\\Users\\Maxime\\.cargo\\registry\\src\\github.com-1ecc6299db9ec823\\rustc_version-0.1.7\\src\\lib.rs","parent":null,"children":[{"krate":0,"index":1},{"krate":0,"index":2},{"krate":0,"index":3},{"krate":0,"index":4},{"krate":0,"index":5},{"krate":0,"index":6},{"krate":0,"index":7},{"krate":0,"index":8},{"krate":0,"index":9},{"krate":0,"index":107},{"krate":0,"index":10},{"krate":0,"index":20},{"krate":0,"index":46},{"krate":0,"index":44},{"krate":0,"index":41},{"krate":0,"index":42},{"krate":0,"index":38},{"krate":0,"index":39},{"krate":0,"index":36},{"krate":0,"index":34},{"krate":0,"index":31},{"krate":0,"index":29},{"krate":0,"index":47},{"krate":0,"index":97},{"krate":0,"index":94},{"krate":0,"index":95},{"krate":0,"index":90},{"krate":0,"index":91},{"krate":0,"index":88},{"krate":0,"index":58},{"krate":0,"index":55},{"krate":0,"index":11},{"krate":0,"index":12},{"krate":0,"index":15},{"krate":0,"index":19}],"decl_id":null,"docs":" Simple library for getting the version information of a `rustc`\n compiler.","sig":null,"attributes":[{"value":"warn(missing_docs)","span":{"file_name":"C:\\Users\\Maxime\\.cargo\\registry\\src\\github.com-1ecc6299db9ec823\\rustc_version-0.1.7\\src\\lib.rs","byte_start":350,"byte_end":372,"line_start":9,"line_end":9,"column_start":1,"column_end":23}},{"value":"/ Simple library for getting the version information of a `rustc`","span":{"file_name":"C:\\Users\\Maxime\\.cargo\\registry\\src\\github.com-1ecc6299db9ec823\\rustc_version-0.1.7\\src\\lib.rs","byte_start":374,"byte_end":441,"line_start":11,"line_end":11,"column_start":1,"column_end":68}},{"value":"/ compiler.","span":{"file_name":"C:\\Users\\Maxime\\.cargo\\registry\\src\\github.com-1ecc6299db9ec823\\rustc_version-0.1.7\\src\\lib.rs","byte_start":442,"byte_end":455,"line_start":12,"line_end":12,"column_start":1,"column_end":14}},{"value":"/","span":{"file_name":"C:\\Users\\Maxime\\.cargo\\registry\\src\\github.com-1ecc6299db9ec823\\rustc_version-0.1.7\\src\\lib.rs","byte_start":456,"byte_end":459,"line_start":13,"line_end":13,"column_start":1,"column_end":4}},{"value":"/ This calls `$RUSTC --version` and parses the output, falling","span":{"file_name":"C:\\Users\\Maxime\\.cargo\\registry\\src\\github.com-1ecc6299db9ec823\\rustc_version-0.1.7\\src\\lib.rs","byte_start":460,"byte_end":524,"line_start":14,"line_end":14,"column_start":1,"column_end":65}},{"value":"/ back to `rustc` if `$RUSTC` is not set.","span":{"file_name":"C:\\Users\\Maxime\\.cargo\\registry\\src\\github.com-1ecc6299db9ec823\\rustc_version-0.1.7\\src\\lib.rs","byte_start":525,"byte_end":568,"line_start":15,"line_end":15,"column_start":1,"column_end":44}},{"value":"/","span":{"file_name":"C:\\Users\\Maxime\\.cargo\\registry\\src\\github.com-1ecc6299db9ec823\\rustc_version-0.1.7\\src\\lib.rs","byte_start":569,"byte_end":572,"line_start":16,"line_end":16,"column_start":1,"column_end":4}},{"value":"/ # Example","span":{"file_name":"C:\\Users\\Maxime\\.cargo\\registry\\src\\github.com-1ecc6299db9ec823\\rustc_version-0.1.7\\src\\lib.rs","byte_start":573,"byte_end":586,"line_start":17,"line_end":17,"column_start":1,"column_end":14}},{"value":"/","span":{"file_name":"C:\\Users\\Maxime\\.cargo\\registry\\src\\github.com-1ecc6299db9ec823\\rustc_version-0.1.7\\src\\lib.rs","byte_start":587,"byte_end":590,"line_start":18,"line_end":18,"column_start":1,"column_end":4}},{"value":"/ ```rust","span":{"file_name":"C:\\Users\\Maxime\\.cargo\\registry\\src\\github.com-1ecc6299db9ec823\\rustc_version-0.1.7\\src\\lib.rs","byte_start":591,"byte_end":602,"line_start":19,"line_end":19,"column_start":1,"column_end":12}},{"value":"/ // This could be a cargo build script","span":{"file_name":"C:\\Users\\Maxime\\.cargo\\registry\\src\\github.com-1ecc6299db9ec823\\rustc_version-0.1.7\\src\\lib.rs","byte_start":603,"byte_end":644,"line_start":20,"line_end":20,"column_start":1,"column_end":42}},{"value":"/","span":{"file_name":"C:\\Users\\Maxime\\.cargo\\registry\\src\\github.com-1ecc6299db9ec823\\rustc_version-0.1.7\\src\\lib.rs","byte_start":645,"byte_end":648,"line_start":21,"line_end":21,"column_start":1,"column_end":4}},{"value":"/ extern crate rustc_version;","span":{"file_name":"C:\\Users\\Maxime\\.cargo\\registry\\src\\github.com-1ecc6299db9ec823\\rustc_version-0.1.7\\src\\lib.rs","byte_start":649,"byte_end":680,"line_start":22,"line_end":22,"column_start":1,"column_end":32}},{"value":"/ use rustc_version::{version, version_matches, version_meta, Channel};","span":{"file_name":"C:\\Users\\Maxime\\.cargo\\registry\\src\\github.com-1ecc6299db9ec823\\rustc_version-0.1.7\\src\\lib.rs","byte_start":681,"byte_end":754,"line_start":23,"line_end":23,"column_start":1,"column_end":74}},{"value":"/","span":{"file_name":"C:\\Users\\Maxime\\.cargo\\registry\\src\\github.com-1ecc6299db9ec823\\rustc_version-0.1.7\\src\\lib.rs","byte_start":755,"byte_end":758,"line_start":24,"line_end":24,"column_start":1,"column_end":4}},{"value":"/ fn main() {","span":{"file_name":"C:\\Users\\Maxime\\.cargo\\registry\\src\\github.com-1ecc6299db9ec823\\rustc_version-0.1.7\\src\\lib.rs","byte_start":759,"byte_end":774,"line_start":25,"line_end":25,"column_start":1,"column_end":16}},{"value":"/     // Assert we haven't travelled back in time","span":{"file_name":"C:\\Users\\Maxime\\.cargo\\registry\\src\\github.com-1ecc6299db9ec823\\rustc_version-0.1.7\\src\\lib.rs","byte_start":775,"byte_end":826,"line_start":26,"line_end":26,"column_start":1,"column_end":52}},{"value":"/     assert!(version().major >= 1);","span":{"file_name":"C:\\Users\\Maxime\\.cargo\\registry\\src\\github.com-1ecc6299db9ec823\\rustc_version-0.1.7\\src\\lib.rs","byte_start":827,"byte_end":865,"line_start":27,"line_end":27,"column_start":1,"column_end":39}},{"value":"/","span":{"file_name":"C:\\Users\\Maxime\\.cargo\\registry\\src\\github.com-1ecc6299db9ec823\\rustc_version-0.1.7\\src\\lib.rs","byte_start":866,"byte_end":869,"line_start":28,"line_end":28,"column_start":1,"column_end":4}},{"value":"/     // Set cfg flags depending on release channel","span":{"file_name":"C:\\Users\\Maxime\\.cargo\\registry\\src\\github.com-1ecc6299db9ec823\\rustc_version-0.1.7\\src\\lib.rs","byte_start":870,"byte_end":923,"line_start":29,"line_end":29,"column_start":1,"column_end":54}},{"value":"/     match version_meta().channel {","span":{"file_name":"C:\\Users\\Maxime\\.cargo\\registry\\src\\github.com-1ecc6299db9ec823\\rustc_version-0.1.7\\src\\lib.rs","byte_start":924,"byte_end":962,"line_start":30,"line_end":30,"column_start":1,"column_end":39}},{"value":"/         Channel::Stable => {","span":{"file_name":"C:\\Users\\Maxime\\.cargo\\registry\\src\\github.com-1ecc6299db9ec823\\rustc_version-0.1.7\\src\\lib.rs","byte_start":963,"byte_end":995,"line_start":31,"line_end":31,"column_start":1,"column_end":33}},{"value":"/             println!(\"cargo:rustc-cfg=RUSTC_IS_STABLE\");","span":{"file_name":"C:\\Users\\Maxime\\.cargo\\registry\\src\\github.com-1ecc6299db9ec823\\rustc_version-0.1.7\\src\\lib.rs","byte_start":996,"byte_end":1056,"line_start":32,"line_end":32,"column_start":1,"column_end":61}},{"value":"/         }","span":{"file_name":"C:\\Users\\Maxime\\.cargo\\registry\\src\\github.com-1ecc6299db9ec823\\rustc_version-0.1.7\\src\\lib.rs","byte_start":1057,"byte_end":1070,"line_start":33,"line_end":33,"column_start":1,"column_end":14}},{"value":"/         Channel::Beta => {","span":{"file_name":"C:\\Users\\Maxime\\.cargo\\registry\\src\\github.com-1ecc6299db9ec823\\rustc_version-0.1.7\\src\\lib.rs","byte_start":1071,"byte_end":1101,"line_start":34,"line_end":34,"column_start":1,"column_end":31}},{"value":"/             println!(\"cargo:rustc-cfg=RUSTC_IS_BETA\");","span":{"file_name":"C:\\Users\\Maxime\\.cargo\\registry\\src\\github.com-1ecc6299db9ec823\\rustc_version-0.1.7\\src\\lib.rs","byte_start":1102,"byte_end":1160,"line_start":35,"line_end":35,"column_start":1,"column_end":59}},{"value":"/         }","span":{"file_name":"C:\\Users\\Maxime\\.cargo\\registry\\src\\github.com-1ecc6299db9ec823\\rustc_version-0.1.7\\src\\lib.rs","byte_start":1161,"byte_end":1174,"line_start":36,"line_end":36,"column_start":1,"column_end":14}},{"value":"/         Channel::Nightly => {","span":{"file_name":"C:\\Users\\Maxime\\.cargo\\registry\\src\\github.com-1ecc6299db9ec823\\rustc_version-0.1.7\\src\\lib.rs","byte_start":1175,"byte_end":1208,"line_start":37,"line_end":37,"column_start":1,"column_end":34}},{"value":"/             println!(\"cargo:rustc-cfg=RUSTC_IS_NIGHTLY\");","span":{"file_name":"C:\\Users\\Maxime\\.cargo\\registry\\src\\github.com-1ecc6299db9ec823\\rustc_version-0.1.7\\src\\lib.rs","byte_start":1209,"byte_end":1270,"line_start":38,"line_end":38,"column_start":1,"column_end":62}},{"value":"/         }","span":{"file_name":"C:\\Users\\Maxime\\.cargo\\registry\\src\\github.com-1ecc6299db9ec823\\rustc_version-0.1.7\\src\\lib.rs","byte_start":1271,"byte_end":1284,"line_start":39,"line_end":39,"column_start":1,"column_end":14}},{"value":"/         Channel::Dev => {","span":{"file_name":"C:\\Users\\Maxime\\.cargo\\registry\\src\\github.com-1ecc6299db9ec823\\rustc_version-0.1.7\\src\\lib.rs","byte_start":1285,"byte_end":1314,"line_start":40,"line_end":40,"column_start":1,"column_end":30}},{"value":"/             println!(\"cargo:rustc-cfg=RUSTC_IS_DEV\");","span":{"file_name":"C:\\Users\\Maxime\\.cargo\\registry\\src\\github.com-1ecc6299db9ec823\\rustc_version-0.1.7\\src\\lib.rs","byte_start":1315,"byte_end":1372,"line_start":41,"line_end":41,"column_start":1,"column_end":58}},{"value":"/         }","span":{"file_name":"C:\\Users\\Maxime\\.cargo\\registry\\src\\github.com-1ecc6299db9ec823\\rustc_version-0.1.7\\src\\lib.rs","byte_start":1373,"byte_end":1386,"line_start":42,"line_end":42,"column_start":1,"column_end":14}},{"value":"/     }","span":{"file_name":"C:\\Users\\Maxime\\.cargo\\registry\\src\\github.com-1ecc6299db9ec823\\rustc_version-0.1.7\\src\\lib.rs","byte_start":1387,"byte_end":1396,"line_start":43,"line_end":43,"column_start":1,"column_end":10}},{"value":"/","span":{"file_name":"C:\\Users\\Maxime\\.cargo\\registry\\src\\github.com-1ecc6299db9ec823\\rustc_version-0.1.7\\src\\lib.rs","byte_start":1397,"byte_end":1400,"line_start":44,"line_end":44,"column_start":1,"column_end":4}},{"value":"/     // Directly check a semver version requirment","span":{"file_name":"C:\\Users\\Maxime\\.cargo\\registry\\src\\github.com-1ecc6299db9ec823\\rustc_version-0.1.7\\src\\lib.rs","byte_start":1401,"byte_end":1454,"line_start":45,"line_end":45,"column_start":1,"column_end":54}},{"value":"/     if version_matches(\">= 1.4.0\") {","span":{"file_name":"C:\\Users\\Maxime\\.cargo\\registry\\src\\github.com-1ecc6299db9ec823\\rustc_version-0.1.7\\src\\lib.rs","byte_start":1455,"byte_end":1495,"line_start":46,"line_end":46,"column_start":1,"column_end":41}},{"value":"/         println!(\"cargo:rustc-cfg=compiler_has_important_bugfix\");","span":{"file_name":"C:\\Users\\Maxime\\.cargo\\registry\\src\\github.com-1ecc6299db9ec823\\rustc_version-0.1.7\\src\\lib.rs","byte_start":1496,"byte_end":1566,"line_start":47,"line_end":47,"column_start":1,"column_end":71}},{"value":"/     }","span":{"file_name":"C:\\Users\\Maxime\\.cargo\\registry\\src\\github.com-1ecc6299db9ec823\\rustc_version-0.1.7\\src\\lib.rs","byte_start":1567,"byte_end":1576,"line_start":48,"line_end":48,"column_start":1,"column_end":10}},{"value":"/ }","span":{"file_name":"C:\\Users\\Maxime\\.cargo\\registry\\src\\github.com-1ecc6299db9ec823\\rustc_version-0.1.7\\src\\lib.rs","byte_start":1577,"byte_end":1582,"line_start":49,"line_end":49,"column_start":1,"column_end":6}},{"value":"/ ```","span":{"file_name":"C:\\Users\\Maxime\\.cargo\\registry\\src\\github.com-1ecc6299db9ec823\\rustc_version-0.1.7\\src\\lib.rs","byte_start":1583,"byte_end":1590,"line_start":50,"line_end":50,"column_start":1,"column_end":8}}]},{"kind":"TupleVariant","id":{"krate":0,"index":21},"span":{"file_name":"C:\\Users\\Maxime\\.cargo\\registry\\src\\github.com-1ecc6299db9ec823\\rustc_version-0.1.7\\src\\lib.rs","byte_start":1890,"byte_end":1893,"line_start":62,"line_end":62,"column_start":5,"column_end":8},"name":"Dev","qualname":"::Channel::Dev","value":"Channel::Dev","parent":{"krate":0,"index":20},"children":[],"decl_id":null,"docs":" Development release channel\n","sig":null,"attributes":[{"value":"/ Development release channel","span":{"file_name":"C:\\Users\\Maxime\\.cargo\\registry\\src\\github.com-1ecc6299db9ec823\\rustc_version-0.1.7\\src\\lib.rs","byte_start":1854,"byte_end":1885,"line_start":61,"line_end":61,"column_start":5,"column_end":36}}]},{"kind":"TupleVariant","id":{"krate":0,"index":23},"span":{"file_name":"C:\\Users\\Maxime\\.cargo\\registry\\src\\github.com-1ecc6299db9ec823\\rustc_version-0.1.7\\src\\lib.rs","byte_start":1931,"byte_end":1938,"line_start":64,"line_end":64,"column_start":5,"column_end":12},"name":"Nightly","qualname":"::Channel::Nightly","value":"Channel::Nightly","parent":{"krate":0,"index":20},"children":[],"decl_id":null,"docs":" Nightly release channel\n","sig":null,"attributes":[{"value":"/ Nightly release channel","span":{"file_name":"C:\\Users\\Maxime\\.cargo\\registry\\src\\github.com-1ecc6299db9ec823\\rustc_version-0.1.7\\src\\lib.rs","byte_start":1899,"byte_end":1926,"line_start":63,"line_end":63,"column_start":5,"column_end":32}}]},{"kind":"TupleVariant","id":{"krate":0,"index":25},"span":{"file_name":"C:\\Users\\Maxime\\.cargo\\registry\\src\\github.com-1ecc6299db9ec823\\rustc_version-0.1.7\\src\\lib.rs","byte_start":1973,"byte_end":1977,"line_start":66,"line_end":66,"column_start":5,"column_end":9},"name":"Beta","qualname":"::Channel::Beta","value":"Channel::Beta","parent":{"krate":0,"index":20},"children":[],"decl_id":null,"docs":" Beta release channel\n","sig":null,"attributes":[{"value":"/ Beta release channel","span":{"file_name":"C:\\Users\\Maxime\\.cargo\\registry\\src\\github.com-1ecc6299db9ec823\\rustc_version-0.1.7\\src\\lib.rs","byte_start":1944,"byte_end":1968,"line_start":65,"line_end":65,"column_start":5,"column_end":29}}]},{"kind":"TupleVariant","id":{"krate":0,"index":27},"span":{"file_name":"C:\\Users\\Maxime\\.cargo\\registry\\src\\github.com-1ecc6299db9ec823\\rustc_version-0.1.7\\src\\lib.rs","byte_start":2014,"byte_end":2020,"line_start":68,"line_end":68,"column_start":5,"column_end":11},"name":"Stable","qualname":"::Channel::Stable","value":"Channel::Stable","parent":{"krate":0,"index":20},"children":[],"decl_id":null,"docs":" Stable release channel\n","sig":null,"attributes":[{"value":"/ Stable release channel","span":{"file_name":"C:\\Users\\Maxime\\.cargo\\registry\\src\\github.com-1ecc6299db9ec823\\rustc_version-0.1.7\\src\\lib.rs","byte_start":1983,"byte_end":2009,"line_start":67,"line_end":67,"column_start":5,"column_end":31}}]},{"kind":"Enum","id":{"krate":0,"index":20},"span":{"file_name":"C:\\Users\\Maxime\\.cargo\\registry\\src\\github.com-1ecc6299db9ec823\\rustc_version-0.1.7\\src\\lib.rs","byte_start":1840,"byte_end":1847,"line_start":60,"line_end":60,"column_start":10,"column_end":17},"name":"Channel","qualname":"::Channel","value":"pub enum Channel {\n\n    /// Development release channel\n    Dev,\n\n    /// Nightly release channel\n    Nightly,\n\n    /// Beta release channel\n    Beta,\n\n    /// Stable release channel\n    Stable,\n}","parent":null,"children":[{"krate":0,"index":21},{"krate":0,"index":23},{"krate":0,"index":25},{"krate":0,"index":27}],"decl_id":null,"docs":" Release channel of the compiler.\n","sig":null,"attributes":[{"value":"/ Release channel of the compiler.","span":{"file_name":"C:\\Users\\Maxime\\.cargo\\registry\\src\\github.com-1ecc6299db9ec823\\rustc_version-0.1.7\\src\\lib.rs","byte_start":1726,"byte_end":1762,"line_start":58,"line_end":58,"column_start":1,"column_end":37}}]},{"kind":"Struct","id":{"krate":0,"index":47},"span":{"file_name":"C:\\Users\\Maxime\\.cargo\\registry\\src\\github.com-1ecc6299db9ec823\\rustc_version-0.1.7\\src\\lib.rs","byte_start":2157,"byte_end":2168,"line_start":73,"line_end":73,"column_start":12,"column_end":23},"name":"VersionMeta","qualname":"::VersionMeta","value":"VersionMeta { semver, commit_hash, commit_date, build_date, channel, host, short_version_string }","parent":null,"children":[{"krate":0,"index":48},{"krate":0,"index":49},{"krate":0,"index":50},{"krate":0,"index":51},{"krate":0,"index":52},{"krate":0,"index":53},{"krate":0,"index":54}],"decl_id":null,"docs":" Rustc version plus metada like git short hash and build date.\n","sig":null,"attributes":[{"value":"/ Rustc version plus metada like git short hash and build date.","span":{"file_name":"C:\\Users\\Maxime\\.cargo\\registry\\src\\github.com-1ecc6299db9ec823\\rustc_version-0.1.7\\src\\lib.rs","byte_start":2025,"byte_end":2090,"line_start":71,"line_end":71,"column_start":1,"column_end":66}}]},{"kind":"Field","id":{"krate":0,"index":48},"span":{"file_name":"C:\\Users\\Maxime\\.cargo\\registry\\src\\github.com-1ecc6299db9ec823\\rustc_version-0.1.7\\src\\lib.rs","byte_start":2211,"byte_end":2217,"line_start":75,"line_end":75,"column_start":9,"column_end":15},"name":"semver","qualname":"::VersionMeta::semver","value":"semver::Version","parent":{"krate":0,"index":47},"children":[],"decl_id":null,"docs":" Version of the compiler\n","sig":null,"attributes":[{"value":"/ Version of the compiler","span":{"file_name":"C:\\Users\\Maxime\\.cargo\\registry\\src\\github.com-1ecc6299db9ec823\\rustc_version-0.1.7\\src\\lib.rs","byte_start":2175,"byte_end":2202,"line_start":74,"line_end":74,"column_start":5,"column_end":32}}]},{"kind":"Field","id":{"krate":0,"index":49},"span":{"file_name":"C:\\Users\\Maxime\\.cargo\\registry\\src\\github.com-1ecc6299db9ec823\\rustc_version-0.1.7\\src\\lib.rs","byte_start":2289,"byte_end":2300,"line_start":78,"line_end":78,"column_start":9,"column_end":20},"name":"commit_hash","qualname":"::VersionMeta::commit_hash","value":"std::option::Option<std::string::String>","parent":{"krate":0,"index":47},"children":[],"decl_id":null,"docs":" Git short hash of the build of the compiler\n","sig":null,"attributes":[{"value":"/ Git short hash of the build of the compiler","span":{"file_name":"C:\\Users\\Maxime\\.cargo\\registry\\src\\github.com-1ecc6299db9ec823\\rustc_version-0.1.7\\src\\lib.rs","byte_start":2233,"byte_end":2280,"line_start":77,"line_end":77,"column_start":5,"column_end":52}}]},{"kind":"Field","id":{"krate":0,"index":50},"span":{"file_name":"C:\\Users\\Maxime\\.cargo\\registry\\src\\github.com-1ecc6299db9ec823\\rustc_version-0.1.7\\src\\lib.rs","byte_start":2363,"byte_end":2374,"line_start":81,"line_end":81,"column_start":9,"column_end":20},"name":"commit_date","qualname":"::VersionMeta::commit_date","value":"std::option::Option<std::string::String>","parent":{"krate":0,"index":47},"children":[],"decl_id":null,"docs":" Commit date of the compiler\n","sig":null,"attributes":[{"value":"/ Commit date of the compiler","span":{"file_name":"C:\\Users\\Maxime\\.cargo\\registry\\src\\github.com-1ecc6299db9ec823\\rustc_version-0.1.7\\src\\lib.rs","byte_start":2323,"byte_end":2354,"line_start":80,"line_end":80,"column_start":5,"column_end":36}}]},{"kind":"Field","id":{"krate":0,"index":51},"span":{"file_name":"C:\\Users\\Maxime\\.cargo\\registry\\src\\github.com-1ecc6299db9ec823\\rustc_version-0.1.7\\src\\lib.rs","byte_start":2484,"byte_end":2494,"line_start":84,"line_end":84,"column_start":9,"column_end":19},"name":"build_date","qualname":"::VersionMeta::build_date","value":"std::option::Option<std::string::String>","parent":{"krate":0,"index":47},"children":[],"decl_id":null,"docs":" Build date of the compiler; this was removed between Rust 1.0.0 and 1.1.0.\n","sig":null,"attributes":[{"value":"/ Build date of the compiler; this was removed between Rust 1.0.0 and 1.1.0.","span":{"file_name":"C:\\Users\\Maxime\\.cargo\\registry\\src\\github.com-1ecc6299db9ec823\\rustc_version-0.1.7\\src\\lib.rs","byte_start":2397,"byte_end":2475,"line_start":83,"line_end":83,"column_start":5,"column_end":83}}]},{"kind":"Field","id":{"krate":0,"index":52},"span":{"file_name":"C:\\Users\\Maxime\\.cargo\\registry\\src\\github.com-1ecc6299db9ec823\\rustc_version-0.1.7\\src\\lib.rs","byte_start":2561,"byte_end":2568,"line_start":87,"line_end":87,"column_start":9,"column_end":16},"name":"channel","qualname":"::VersionMeta::channel","value":"Channel","parent":{"krate":0,"index":47},"children":[],"decl_id":null,"docs":" Release channel of the compiler\n","sig":null,"attributes":[{"value":"/ Release channel of the compiler","span":{"file_name":"C:\\Users\\Maxime\\.cargo\\registry\\src\\github.com-1ecc6299db9ec823\\rustc_version-0.1.7\\src\\lib.rs","byte_start":2517,"byte_end":2552,"line_start":86,"line_end":86,"column_start":5,"column_end":40}}]},{"kind":"Field","id":{"krate":0,"index":53},"span":{"file_name":"C:\\Users\\Maxime\\.cargo\\registry\\src\\github.com-1ecc6299db9ec823\\rustc_version-0.1.7\\src\\lib.rs","byte_start":2631,"byte_end":2635,"line_start":90,"line_end":90,"column_start":9,"column_end":13},"name":"host","qualname":"::VersionMeta::host","value":"std::string::String","parent":{"krate":0,"index":47},"children":[],"decl_id":null,"docs":" Host target triple of the compiler\n","sig":null,"attributes":[{"value":"/ Host target triple of the compiler","span":{"file_name":"C:\\Users\\Maxime\\.cargo\\registry\\src\\github.com-1ecc6299db9ec823\\rustc_version-0.1.7\\src\\lib.rs","byte_start":2584,"byte_end":2622,"line_start":89,"line_end":89,"column_start":5,"column_end":43}}]},{"kind":"Field","id":{"krate":0,"index":54},"span":{"file_name":"C:\\Users\\Maxime\\.cargo\\registry\\src\\github.com-1ecc6299db9ec823\\rustc_version-0.1.7\\src\\lib.rs","byte_start":2699,"byte_end":2719,"line_start":93,"line_end":93,"column_start":9,"column_end":29},"name":"short_version_string","qualname":"::VersionMeta::short_version_string","value":"std::string::String","parent":{"krate":0,"index":47},"children":[],"decl_id":null,"docs":" Short version string of the compiler\n","sig":null,"attributes":[{"value":"/ Short version string of the compiler","span":{"file_name":"C:\\Users\\Maxime\\.cargo\\registry\\src\\github.com-1ecc6299db9ec823\\rustc_version-0.1.7\\src\\lib.rs","byte_start":2650,"byte_end":2690,"line_start":92,"line_end":92,"column_start":5,"column_end":45}}]},{"kind":"Function","id":{"krate":0,"index":11},"span":{"file_name":"C:\\Users\\Maxime\\.cargo\\registry\\src\\github.com-1ecc6299db9ec823\\rustc_version-0.1.7\\src\\lib.rs","byte_start":2779,"byte_end":2786,"line_start":97,"line_end":97,"column_start":8,"column_end":15},"name":"version","qualname":"::version","value":"pub fn version() -> Version","parent":null,"children":[],"decl_id":null,"docs":" Returns the `rustc` SemVer version.\n","sig":null,"attributes":[{"value":"/ Returns the `rustc` SemVer version.","span":{"file_name":"C:\\Users\\Maxime\\.cargo\\registry\\src\\github.com-1ecc6299db9ec823\\rustc_version-0.1.7\\src\\lib.rs","byte_start":2732,"byte_end":2771,"line_start":96,"line_end":96,"column_start":1,"column_end":40}}]},{"kind":"Function","id":{"krate":0,"index":12},"span":{"file_name":"C:\\Users\\Maxime\\.cargo\\registry\\src\\github.com-1ecc6299db9ec823\\rustc_version-0.1.7\\src\\lib.rs","byte_start":2945,"byte_end":2957,"line_start":103,"line_end":103,"column_start":8,"column_end":20},"name":"version_meta","qualname":"::version_meta","value":"pub fn version_meta() -> VersionMeta","parent":null,"children":[],"decl_id":null,"docs":" Returns the `rustc` SemVer version and additional metadata\n like the git short hash and build date.\n","sig":null,"attributes":[{"value":"/ Returns the `rustc` SemVer version and additional metadata","span":{"file_name":"C:\\Users\\Maxime\\.cargo\\registry\\src\\github.com-1ecc6299db9ec823\\rustc_version-0.1.7\\src\\lib.rs","byte_start":2831,"byte_end":2893,"line_start":101,"line_end":101,"column_start":1,"column_end":63}},{"value":"/ like the git short hash and build date.","span":{"file_name":"C:\\Users\\Maxime\\.cargo\\registry\\src\\github.com-1ecc6299db9ec823\\rustc_version-0.1.7\\src\\lib.rs","byte_start":2894,"byte_end":2937,"line_start":102,"line_end":102,"column_start":1,"column_end":44}}]},{"kind":"Function","id":{"krate":0,"index":15},"span":{"file_name":"C:\\Users\\Maxime\\.cargo\\registry\\src\\github.com-1ecc6299db9ec823\\rustc_version-0.1.7\\src\\lib.rs","byte_start":3499,"byte_end":3515,"line_start":121,"line_end":121,"column_start":8,"column_end":24},"name":"version_meta_for","qualname":"::version_meta_for","value":"pub fn version_meta_for(&str) -> VersionMeta","parent":null,"children":[],"decl_id":null,"docs":" Parses a \"rustc -vV\" output string and returns\n the SemVer version and additional metadata\n like the git short hash and build date.\n","sig":null,"attributes":[{"value":"/ Parses a \"rustc -vV\" output string and returns","span":{"file_name":"C:\\Users\\Maxime\\.cargo\\registry\\src\\github.com-1ecc6299db9ec823\\rustc_version-0.1.7\\src\\lib.rs","byte_start":3350,"byte_end":3400,"line_start":118,"line_end":118,"column_start":1,"column_end":51}},{"value":"/ the SemVer version and additional metadata","span":{"file_name":"C:\\Users\\Maxime\\.cargo\\registry\\src\\github.com-1ecc6299db9ec823\\rustc_version-0.1.7\\src\\lib.rs","byte_start":3401,"byte_end":3447,"line_start":119,"line_end":119,"column_start":1,"column_end":47}},{"value":"/ like the git short hash and build date.","span":{"file_name":"C:\\Users\\Maxime\\.cargo\\registry\\src\\github.com-1ecc6299db9ec823\\rustc_version-0.1.7\\src\\lib.rs","byte_start":3448,"byte_end":3491,"line_start":120,"line_end":120,"column_start":1,"column_end":44}}]},{"kind":"Function","id":{"krate":0,"index":19},"span":{"file_name":"C:\\Users\\Maxime\\.cargo\\registry\\src\\github.com-1ecc6299db9ec823\\rustc_version-0.1.7\\src\\lib.rs","byte_start":5572,"byte_end":5587,"line_start":190,"line_end":190,"column_start":8,"column_end":23},"name":"version_matches","qualname":"::version_matches","value":"pub fn version_matches(&str) -> bool","parent":null,"children":[],"decl_id":null,"docs":" Check wether the `rustc` version matches the given SemVer\n version requirement.\n","sig":null,"attributes":[{"value":"/ Check wether the `rustc` version matches the given SemVer","span":{"file_name":"C:\\Users\\Maxime\\.cargo\\registry\\src\\github.com-1ecc6299db9ec823\\rustc_version-0.1.7\\src\\lib.rs","byte_start":5478,"byte_end":5539,"line_start":188,"line_end":188,"column_start":1,"column_end":62}},{"value":"/ version requirement.","span":{"file_name":"C:\\Users\\Maxime\\.cargo\\registry\\src\\github.com-1ecc6299db9ec823\\rustc_version-0.1.7\\src\\lib.rs","byte_start":5540,"byte_end":5564,"line_start":189,"line_end":189,"column_start":1,"column_end":25}}]}],"impls":[],"refs":[],"macro_refs":[],"relations":[]}